fantex/FanTeX.pdf
fantex/FanTeX.tex
fantex/__init__.py
fantex/editor.py
fantex/fsviewer.py
fantex/gen_FanTeX_pdf.py
fantex/main.py
fantex/mainwindow.py
fantex/pdfviewer.py
fantex-0.0.1.dev1.dist-info/METADATA
fantex-0.0.1.dev1.dist-info/WHEEL
fantex-0.0.1.dev1.dist-info/licenses/LICENSE
fantex-0.0.1.dev1.dist-info/RECORD
