Metadata-Version: 2.1
Name: FanTeX
Version: 0.0.1.dev1
Summary: A TeX editor for scientific writing.
Project-URL: Homepage, https://github.com/mgao6767/FanTeX
Project-URL: Bug Tracker, https://github.com/mgao6767/FanTeX/issues
Author-email: Mingze Gao <mingze.gao@sydney.edu.au>
License: MIT License
Classifier: License :: OSI Approved :: MIT License
Classifier: Operating System :: OS Independent
Classifier: Programming Language :: Python :: 3
Requires-Python: >=3.10
Requires-Dist: pygments==2.12.0
Requires-Dist: pylatex==1.4.1
Requires-Dist: pymupdf==1.20.1
Requires-Dist: pyqt6==6.3.1
